[
{"Name":"[JP] Black Desert - Eternal Winter Edition","NameSEO":"jp-black-desert---eternal-winter-edition","Source":"steam","AppId":"1920984","Logo":"https://gamecharts.org/data/steam/img/1920984/header.jpg"},
{"Name":"[JP] Explorer to Conqueror DLC","NameSEO":"jp-explorer-to-conqueror-dlc","Source":"steam","AppId":"1914091","Logo":"https://gamecharts.org/data/steam/img/1914091/header.jpg"},
{"Name":"[JP] Traveler to Conqueror DLC","NameSEO":"jp-traveler-to-conqueror-dlc","Source":"steam","AppId":"1914092","Logo":"https://gamecharts.org/data/steam/img/1914092/header.jpg"},
{"Name":"[JP] Traveler to Explorer DLC","NameSEO":"jp-traveler-to-explorer-dlc","Source":"steam","AppId":"1914090","Logo":"https://gamecharts.org/data/steam/img/1914090/header.jpg"},
{"Name":"[JP] 黒い砂漠 - 無料プレゼントパッケージ","NameSEO":"jp-黒い砂漠---無料プレゼントパッケージ","Source":"steam","AppId":"1782370","Logo":"https://gamecharts.org/data/steam/img/1782370/header.jpg"}
]
