[
{"Name":"PH0B0S","NameSEO":"ph0b0s","Source":"steam","AppId":"1978750","Logo":"https://gamecharts.org/data/steam/img/1978750/header.jpg"},
{"Name":"PHAGEBORN online card game","NameSEO":"phageborn-online-card-game","Source":"steam","AppId":"1037990","Logo":"https://gamecharts.org/data/steam/img/1037990/header.jpg"},
{"Name":"Phageborn Online Card Game - Supporter Pack","NameSEO":"phageborn-online-card-game---supporter-pack","Source":"steam","AppId":"1244030","Logo":"https://gamecharts.org/data/steam/img/1244030/header.jpg"},
{"Name":"Phageborn Online Card Game PUBLIC BETA","NameSEO":"phageborn-online-card-game-public-beta","Source":"steam","AppId":"1221580","Logo":"https://gamecharts.org/data/steam/img/1221580/header.jpg"},
{"Name":"PhaigeX: Hyperspace Survivors","NameSEO":"phaigex-hyperspace-survivors","Source":"steam","AppId":"2159500","Logo":"https://gamecharts.org/data/steam/img/2159500/header.jpg"},
{"Name":"Phalanx of Resistance","NameSEO":"phalanx-of-resistance","Source":"steam","AppId":"1236320","Logo":"https://gamecharts.org/data/steam/img/1236320/header.jpg"},
{"Name":"Phanotia I: Escavive","NameSEO":"phanotia-i-escavive","Source":"steam","AppId":"2269420","Logo":"https://gamecharts.org/data/steam/img/2269420/header.jpg"},
{"Name":"Phanotia: Interlude I-Aubzan Abbey","NameSEO":"phanotia-interlude-i-aubzan-abbey","Source":"steam","AppId":"2414530","Logo":"https://gamecharts.org/data/steam/img/2414530/header.jpg"},
{"Name":"Phantaruk","NameSEO":"phantaruk","Source":"steam","AppId":"468930","Logo":"https://gamecharts.org/data/steam/img/468930/header.jpg"},
{"Name":"PHANTASIA","NameSEO":"phantasia","Source":"steam","AppId":"1821820","Logo":"https://gamecharts.org/data/steam/img/1821820/header.jpg"},
{"Name":"Phantasm: MoonCity","NameSEO":"phantasm-mooncity","Source":"steam","AppId":"1318060","Logo":"https://gamecharts.org/data/steam/img/1318060/header.jpg"},
{"Name":"Phantasma VR","NameSEO":"phantasma-vr","Source":"steam","AppId":"608870","Logo":"https://gamecharts.org/data/steam/img/608870/header.jpg"},
{"Name":"Phantasmagoria","NameSEO":"phantasmagoria","Source":"steam","AppId":"501990","Logo":"https://gamecharts.org/data/steam/img/501990/header.jpg"},
{"Name":"Phantasmagoria 2","NameSEO":"phantasmagoria-2","Source":"steam","AppId":"501970","Logo":"https://gamecharts.org/data/steam/img/501970/header.jpg"},
{"Name":"Phantasmal","NameSEO":"phantasmal","Source":"steam","AppId":"342550","Logo":"https://gamecharts.org/data/steam/img/342550/header.jpg"},
{"Name":"Phantasmat: Crucible Peak Collector's Edition","NameSEO":"phantasmat-crucible-peak-collectors-edition","Source":"steam","AppId":"533080","Logo":"https://gamecharts.org/data/steam/img/533080/header.jpg"},
{"Name":"Phantasmat: The Dread of Oakville Collector's Edition","NameSEO":"phantasmat-the-dread-of-oakville-collectors-edition","Source":"steam","AppId":"940980","Logo":"https://gamecharts.org/data/steam/img/940980/header.jpg"},
{"Name":"Phantasmat: The Endless Night Collector's Edition","NameSEO":"phantasmat-the-endless-night-collectors-edition","Source":"steam","AppId":"635520","Logo":"https://gamecharts.org/data/steam/img/635520/header.jpg"},
{"Name":"Phantasmata","NameSEO":"phantasmata","Source":"steam","AppId":"1048790","Logo":"https://gamecharts.org/data/steam/img/1048790/header.jpg"},
{"Name":"Phantast","NameSEO":"phantast","Source":"steam","AppId":"1496120","Logo":"https://gamecharts.org/data/steam/img/1496120/header.jpg"},
{"Name":"Phantasy Star 2","NameSEO":"phantasy-star-2","Source":"steam","AppId":"211203","Logo":"https://gamecharts.org/data/steam/img/211203/header.jpg"},
{"Name":"Phantasy Star 3","NameSEO":"phantasy-star-3","Source":"steam","AppId":"211204","Logo":"https://gamecharts.org/data/steam/img/211204/header.jpg"},
{"Name":"Phantasy Star 4","NameSEO":"phantasy-star-4","Source":"steam","AppId":"211205","Logo":"https://gamecharts.org/data/steam/img/211205/header.jpg"},
{"Name":"Phantasy Star Online 2 New Genesis","NameSEO":"phantasy-star-online-2-new-genesis","Source":"steam","AppId":"1056640","Logo":"https://gamecharts.org/data/steam/img/1056640/header.jpg"},
{"Name":"Phantom","NameSEO":"phantom","Source":"steam","AppId":"578800","Logo":"https://gamecharts.org/data/steam/img/578800/header.jpg"},
{"Name":"Phantom 3D","NameSEO":"phantom-3d","Source":"steam","AppId":"1132930","Logo":"https://gamecharts.org/data/steam/img/1132930/header.jpg"},
{"Name":"Phantom Abyss","NameSEO":"phantom-abyss","Source":"steam","AppId":"989440","Logo":"https://gamecharts.org/data/steam/img/989440/header.jpg"},
{"Name":"Phantom Alchemy ~Silvia's Dynamic Urban Planning~","NameSEO":"phantom-alchemy-~silvias-dynamic-urban-planning~","Source":"steam","AppId":"2074940","Logo":"https://gamecharts.org/data/steam/img/2074940/header.jpg"},
{"Name":"Phantom Astronaut Lucid VR","NameSEO":"phantom-astronaut-lucid-vr","Source":"steam","AppId":"1146810","Logo":"https://gamecharts.org/data/steam/img/1146810/header.jpg"},
{"Name":"Phantom Beasts - PvP Prototype Playtest","NameSEO":"phantom-beasts---pvp-prototype-playtest","Source":"steam","AppId":"1875920","Logo":"https://gamecharts.org/data/steam/img/1875920/header.jpg"},
{"Name":"Phantom Beasts - Redemption","NameSEO":"phantom-beasts---redemption","Source":"steam","AppId":"1483000","Logo":"https://gamecharts.org/data/steam/img/1483000/header.jpg"},
{"Name":"Phantom Beasts - Redemption Playtest","NameSEO":"phantom-beasts---redemption-playtest","Source":"steam","AppId":"1691200","Logo":"https://gamecharts.org/data/steam/img/1691200/header.jpg"},
{"Name":"Phantom Blade: Executioners","NameSEO":"phantom-blade-executioners","Source":"steam","AppId":"2365940","Logo":"https://gamecharts.org/data/steam/img/2365940/header.jpg"},
{"Name":"Phantom Brave PC","NameSEO":"phantom-brave-pc","Source":"steam","AppId":"409870","Logo":"https://gamecharts.org/data/steam/img/409870/header.jpg"},
{"Name":"Phantom Breaker: Battle Grounds","NameSEO":"phantom-breaker-battle-grounds","Source":"steam","AppId":"329490","Logo":"https://gamecharts.org/data/steam/img/329490/header.jpg"},
{"Name":"Phantom Breaker: Omnia","NameSEO":"phantom-breaker-omnia","Source":"steam","AppId":"1184560","Logo":"https://gamecharts.org/data/steam/img/1184560/header.jpg"},
{"Name":"Phantom Brigade","NameSEO":"phantom-brigade","Source":"steam","AppId":"553540","Logo":"https://gamecharts.org/data/steam/img/553540/header.jpg"},
{"Name":"Phantom Brigade Playtest","NameSEO":"phantom-brigade-playtest","Source":"steam","AppId":"1983410","Logo":"https://gamecharts.org/data/steam/img/1983410/header.jpg"},
{"Name":"Phantom Club","NameSEO":"phantom-club","Source":"steam","AppId":"2062610","Logo":"https://gamecharts.org/data/steam/img/2062610/header.jpg"},
{"Name":"Phantom Doctrine","NameSEO":"phantom-doctrine","Source":"steam","AppId":"559100","Logo":"https://gamecharts.org/data/steam/img/559100/header.jpg"},
{"Name":"Phantom Doctrine - Alienware Headwear DLC","NameSEO":"phantom-doctrine---alienware-headwear-dlc","Source":"steam","AppId":"918660","Logo":"https://gamecharts.org/data/steam/img/918660/header.jpg"},
{"Name":"Phantom Doctrine - Alienware Jackets & Shirt DLC","NameSEO":"phantom-doctrine---alienware-jackets--shirt-dlc","Source":"steam","AppId":"918640","Logo":"https://gamecharts.org/data/steam/img/918640/header.jpg"},
{"Name":"Phantom Doctrine - Alienware Vintage Jacket DLC","NameSEO":"phantom-doctrine---alienware-vintage-jacket-dlc","Source":"steam","AppId":"918650","Logo":"https://gamecharts.org/data/steam/img/918650/header.jpg"},
{"Name":"Phantom Doctrine 2: The Cabal","NameSEO":"phantom-doctrine-2-the-cabal","Source":"steam","AppId":"1345450","Logo":"https://gamecharts.org/data/steam/img/1345450/header.jpg"},
{"Name":"Phantom Dwarf","NameSEO":"phantom-dwarf","Source":"steam","AppId":"2422810","Logo":"https://gamecharts.org/data/steam/img/2422810/header.jpg"},
{"Name":"Phantom Flail","NameSEO":"phantom-flail","Source":"steam","AppId":"2339890","Logo":"https://gamecharts.org/data/steam/img/2339890/header.jpg"},
{"Name":"Phantom Fury","NameSEO":"phantom-fury","Source":"steam","AppId":"1733240","Logo":"https://gamecharts.org/data/steam/img/1733240/header.jpg"},
{"Name":"Phantom Gear","NameSEO":"phantom-gear","Source":"steam","AppId":"1802240","Logo":"https://gamecharts.org/data/steam/img/1802240/header.jpg"},
{"Name":"Phantom Halls","NameSEO":"phantom-halls","Source":"steam","AppId":"587920","Logo":"https://gamecharts.org/data/steam/img/587920/header.jpg"},
{"Name":"Phantom Hellcat","NameSEO":"phantom-hellcat","Source":"steam","AppId":"2106730","Logo":"https://gamecharts.org/data/steam/img/2106730/header.jpg"},
{"Name":"Phantom Hills","NameSEO":"phantom-hills","Source":"steam","AppId":"1190720","Logo":"https://gamecharts.org/data/steam/img/1190720/header.jpg"},
{"Name":"Phantom Hunter","NameSEO":"phantom-hunter","Source":"steam","AppId":"2329490","Logo":"https://gamecharts.org/data/steam/img/2329490/header.jpg"},
{"Name":"Phantom Hysteria","NameSEO":"phantom-hysteria","Source":"steam","AppId":"1774770","Logo":"https://gamecharts.org/data/steam/img/1774770/header.jpg"},
{"Name":"Phantom Island","NameSEO":"phantom-island","Source":"steam","AppId":"2121050","Logo":"https://gamecharts.org/data/steam/img/2121050/header.jpg"},
{"Name":"Phantom Jump","NameSEO":"phantom-jump","Source":"steam","AppId":"701440","Logo":"https://gamecharts.org/data/steam/img/701440/header.jpg"},
{"Name":"Phantom Matrix","NameSEO":"phantom-matrix","Source":"steam","AppId":"803640","Logo":"https://gamecharts.org/data/steam/img/803640/header.jpg"},
{"Name":"Phantom of Zana","NameSEO":"phantom-of-zana","Source":"steam","AppId":"2437560","Logo":"https://gamecharts.org/data/steam/img/2437560/header.jpg"},
{"Name":"Phantom of Zana Playtest","NameSEO":"phantom-of-zana-playtest","Source":"steam","AppId":"2462330","Logo":"https://gamecharts.org/data/steam/img/2462330/header.jpg"},
{"Name":"Phantom Path","NameSEO":"phantom-path","Source":"steam","AppId":"1180970","Logo":"https://gamecharts.org/data/steam/img/1180970/header.jpg"},
{"Name":"Phantom Peak","NameSEO":"phantom-peak","Source":"steam","AppId":"2484240","Logo":"https://gamecharts.org/data/steam/img/2484240/header.jpg"},
{"Name":"Phantom Project","NameSEO":"phantom-project","Source":"steam","AppId":"1745480","Logo":"https://gamecharts.org/data/steam/img/1745480/header.jpg"},
{"Name":"Phantom Proxy","NameSEO":"phantom-proxy","Source":"steam","AppId":"1332350","Logo":"https://gamecharts.org/data/steam/img/1332350/header.jpg"},
{"Name":"Phantom Racing","NameSEO":"phantom-racing","Source":"steam","AppId":"1953560","Logo":"https://gamecharts.org/data/steam/img/1953560/header.jpg"},
{"Name":"Phantom Rose","NameSEO":"phantom-rose","Source":"steam","AppId":"1054550","Logo":"https://gamecharts.org/data/steam/img/1054550/header.jpg"},
{"Name":"Phantom Rose 2 Sapphire","NameSEO":"phantom-rose-2-sapphire","Source":"steam","AppId":"1964200","Logo":"https://gamecharts.org/data/steam/img/1964200/header.jpg"},
{"Name":"Phantom sense VR","NameSEO":"phantom-sense-vr","Source":"steam","AppId":"1645670","Logo":"https://gamecharts.org/data/steam/img/1645670/header.jpg"},
{"Name":"Phantom Signal","NameSEO":"phantom-signal","Source":"steam","AppId":"764510","Logo":"https://gamecharts.org/data/steam/img/764510/header.jpg"},
{"Name":"Phantom Tentacle","NameSEO":"phantom-tentacle","Source":"steam","AppId":"1990260","Logo":"https://gamecharts.org/data/steam/img/1990260/header.jpg"},
{"Name":"Phantom Thief Celianna","NameSEO":"phantom-thief-celianna","Source":"steam","AppId":"907210","Logo":"https://gamecharts.org/data/steam/img/907210/header.jpg"},
{"Name":"Phantom Thief Sylphy","NameSEO":"phantom-thief-sylphy","Source":"steam","AppId":"1728550","Logo":"https://gamecharts.org/data/steam/img/1728550/header.jpg"},
{"Name":"Phantom Tides","NameSEO":"phantom-tides","Source":"steam","AppId":"2170410","Logo":"https://gamecharts.org/data/steam/img/2170410/header.jpg"},
{"Name":"Phantom Train","NameSEO":"phantom-train","Source":"steam","AppId":"1656230","Logo":"https://gamecharts.org/data/steam/img/1656230/header.jpg"},
{"Name":"Phantom Trigger","NameSEO":"phantom-trigger","Source":"steam","AppId":"445870","Logo":"https://gamecharts.org/data/steam/img/445870/header.jpg"},
{"Name":"Phantom Typist","NameSEO":"phantom-typist","Source":"steam","AppId":"1439010","Logo":"https://gamecharts.org/data/steam/img/1439010/header.jpg"},
{"Name":"Phantom Wardrobe","NameSEO":"phantom-wardrobe","Source":"steam","AppId":"2481380","Logo":"https://gamecharts.org/data/steam/img/2481380/header.jpg"},
{"Name":"Phantom Warfare","NameSEO":"phantom-warfare","Source":"steam","AppId":"684260","Logo":"https://gamecharts.org/data/steam/img/684260/header.jpg"},
{"Name":"Phantom-OS","NameSEO":"phantom-os","Source":"steam","AppId":"1791080","Logo":"https://gamecharts.org/data/steam/img/1791080/header.jpg"},
{"Name":"Phantomino","NameSEO":"phantomino","Source":"steam","AppId":"1553560","Logo":"https://gamecharts.org/data/steam/img/1553560/header.jpg"},
{"Name":"Pharao Reloaded","NameSEO":"pharao-reloaded","Source":"steam","AppId":"1270280","Logo":"https://gamecharts.org/data/steam/img/1270280/header.jpg"},
{"Name":"Pharaoh + Cleopatra","NameSEO":"pharaoh--cleopatra","Source":"steam","AppId":"564530","Logo":"https://gamecharts.org/data/steam/img/564530/header.jpg"},
{"Name":"Pharaoh Rebirth+","NameSEO":"pharaoh-rebirth","Source":"steam","AppId":"441280","Logo":"https://gamecharts.org/data/steam/img/441280/header.jpg"},
{"Name":"Pharaoh's Tomb","NameSEO":"pharaohs-tomb","Source":"steam","AppId":"358330","Logo":"https://gamecharts.org/data/steam/img/358330/header.jpg"},
{"Name":"Pharaoh: A New Era","NameSEO":"pharaoh-a-new-era","Source":"steam","AppId":"1351080","Logo":"https://gamecharts.org/data/steam/img/1351080/header.jpg"},
{"Name":"Pharaoh: A New Era Playtest","NameSEO":"pharaoh-a-new-era-playtest","Source":"steam","AppId":"1806350","Logo":"https://gamecharts.org/data/steam/img/1806350/header.jpg"},
{"Name":"Pharaonic","NameSEO":"pharaonic","Source":"steam","AppId":"386080","Logo":"https://gamecharts.org/data/steam/img/386080/header.jpg"},
{"Name":"Pharmakon","NameSEO":"pharmakon","Source":"steam","AppId":"654660","Logo":"https://gamecharts.org/data/steam/img/654660/header.jpg"},
{"Name":"Phase 7","NameSEO":"phase-7","Source":"steam","AppId":"499300","Logo":"https://gamecharts.org/data/steam/img/499300/header.jpg"},
{"Name":"Phase Line: Raider Assault","NameSEO":"phase-line-raider-assault","Source":"steam","AppId":"2305050","Logo":"https://gamecharts.org/data/steam/img/2305050/header.jpg"},
{"Name":"Phase Ninja","NameSEO":"phase-ninja","Source":"steam","AppId":"1486370","Logo":"https://gamecharts.org/data/steam/img/1486370/header.jpg"},
{"Name":"Phase Shift","NameSEO":"phase-shift","Source":"steam","AppId":"865250","Logo":"https://gamecharts.org/data/steam/img/865250/header.jpg"},
{"Name":"Phaser","NameSEO":"phaser","Source":"steam","AppId":"1320400","Logo":"https://gamecharts.org/data/steam/img/1320400/header.jpg"},
{"Name":"Phaseshift","NameSEO":"phaseshift","Source":"steam","AppId":"1372730","Logo":"https://gamecharts.org/data/steam/img/1372730/header.jpg"},
{"Name":"PhaseWorm","NameSEO":"phaseworm","Source":"steam","AppId":"1287790","Logo":"https://gamecharts.org/data/steam/img/1287790/header.jpg"},
{"Name":"Phasmophobia","NameSEO":"phasmophobia","Source":"steam","AppId":"739630","Logo":"https://gamecharts.org/data/steam/img/739630/header.jpg"},
{"Name":"PHAT PHROG","NameSEO":"phat-phrog","Source":"steam","AppId":"545570","Logo":"https://gamecharts.org/data/steam/img/545570/header.jpg"},
{"Name":"PHAT STACKS","NameSEO":"phat-stacks","Source":"steam","AppId":"556160","Logo":"https://gamecharts.org/data/steam/img/556160/header.jpg"},
{"Name":"PHAT STACKS 2","NameSEO":"phat-stacks-2","Source":"steam","AppId":"655600","Logo":"https://gamecharts.org/data/steam/img/655600/header.jpg"},
{"Name":"PhD","NameSEO":"phd","Source":"steam","AppId":"2136280","Logo":"https://gamecharts.org/data/steam/img/2136280/header.jpg"},
{"Name":"Pheno[Core]","NameSEO":"phenocore","Source":"steam","AppId":"1939470","Logo":"https://gamecharts.org/data/steam/img/1939470/header.jpg"},
{"Name":"Phenomenal Car Park Simulator","NameSEO":"phenomenal-car-park-simulator","Source":"steam","AppId":"1158860","Logo":"https://gamecharts.org/data/steam/img/1158860/header.jpg"},
{"Name":"Phi","NameSEO":"phi","Source":"steam","AppId":"1483980","Logo":"https://gamecharts.org/data/steam/img/1483980/header.jpg"},
{"Name":"Phijkchu Quest","NameSEO":"phijkchu-quest","Source":"steam","AppId":"2080960","Logo":"https://gamecharts.org/data/steam/img/2080960/header.jpg"},
{"Name":"Phil","NameSEO":"phil","Source":"steam","AppId":"1918810","Logo":"https://gamecharts.org/data/steam/img/1918810/header.jpg"},
{"Name":"Phil Alone","NameSEO":"phil-alone","Source":"steam","AppId":"1902020","Logo":"https://gamecharts.org/data/steam/img/1902020/header.jpg"},
{"Name":"Philana and the Elixir of Life","NameSEO":"philana-and-the-elixir-of-life","Source":"steam","AppId":"1551550","Logo":"https://gamecharts.org/data/steam/img/1551550/header.jpg"},
{"Name":"PhilGood","NameSEO":"philgood","Source":"steam","AppId":"1082620","Logo":"https://gamecharts.org/data/steam/img/1082620/header.jpg"},
{"Name":"Philia : the Sequel to Elansar","NameSEO":"philia--the-sequel-to-elansar","Source":"steam","AppId":"435080","Logo":"https://gamecharts.org/data/steam/img/435080/header.jpg"},
{"Name":"Philomena","NameSEO":"philomena","Source":"steam","AppId":"739860","Logo":"https://gamecharts.org/data/steam/img/739860/header.jpg"},
{"Name":"Philophobia: The Fear of Love","NameSEO":"philophobia-the-fear-of-love","Source":"steam","AppId":"1035950","Logo":"https://gamecharts.org/data/steam/img/1035950/header.jpg"},
{"Name":"Philosopher's Stone and Minerva","NameSEO":"philosophers-stone-and-minerva","Source":"steam","AppId":"1794370","Logo":"https://gamecharts.org/data/steam/img/1794370/header.jpg"},
{"Name":"Philosophical Jigsaw - The Zen Koans","NameSEO":"philosophical-jigsaw---the-zen-koans","Source":"steam","AppId":"1991450","Logo":"https://gamecharts.org/data/steam/img/1991450/header.jpg"},
{"Name":"Philotes Trials","NameSEO":"philotes-trials","Source":"steam","AppId":"2355910","Logo":"https://gamecharts.org/data/steam/img/2355910/header.jpg"},
{"Name":"Phineas and Ferb: New Inventions","NameSEO":"phineas-and-ferb-new-inventions","Source":"steam","AppId":"318300","Logo":"https://gamecharts.org/data/steam/img/318300/header.jpg"},
{"Name":"Phlegethon","NameSEO":"phlegethon","Source":"steam","AppId":"1771060","Logo":"https://gamecharts.org/data/steam/img/1771060/header.jpg"},
{"Name":"Phlyndir","NameSEO":"phlyndir","Source":"steam","AppId":"448990","Logo":"https://gamecharts.org/data/steam/img/448990/header.jpg"},
{"Name":"Pho King My Life","NameSEO":"pho-king-my-life","Source":"steam","AppId":"2474150","Logo":"https://gamecharts.org/data/steam/img/2474150/header.jpg"},
{"Name":"Phobia","NameSEO":"phobia","Source":"steam","AppId":"649150","Logo":"https://gamecharts.org/data/steam/img/649150/header.jpg"},
{"Name":"Phobies","NameSEO":"phobies","Source":"steam","AppId":"1254130","Logo":"https://gamecharts.org/data/steam/img/1254130/header.jpg"},
{"Name":"Phobos","NameSEO":"phobos","Source":"steam","AppId":"1373350","Logo":"https://gamecharts.org/data/steam/img/1373350/header.jpg"},
{"Name":"Phobos - Subhuman","NameSEO":"phobos---subhuman","Source":"steam","AppId":"1759010","Logo":"https://gamecharts.org/data/steam/img/1759010/header.jpg"},
{"Name":"PHOBOS Project","NameSEO":"phobos-project","Source":"steam","AppId":"2014650","Logo":"https://gamecharts.org/data/steam/img/2014650/header.jpg"},
{"Name":"Phobyark","NameSEO":"phobyark","Source":"steam","AppId":"1597750","Logo":"https://gamecharts.org/data/steam/img/1597750/header.jpg"},
{"Name":"Phoenix Dust","NameSEO":"phoenix-dust","Source":"steam","AppId":"1530990","Logo":"https://gamecharts.org/data/steam/img/1530990/header.jpg"},
{"Name":"Phoenix Dynasty 2","NameSEO":"phoenix-dynasty-2","Source":"steam","AppId":"621880","Logo":"https://gamecharts.org/data/steam/img/621880/header.jpg"},
{"Name":"Phoenix Force","NameSEO":"phoenix-force","Source":"steam","AppId":"332480","Logo":"https://gamecharts.org/data/steam/img/332480/header.jpg"},
{"Name":"Phoenix Hope","NameSEO":"phoenix-hope","Source":"steam","AppId":"1465950","Logo":"https://gamecharts.org/data/steam/img/1465950/header.jpg"},
{"Name":"Phoenix Nightmare","NameSEO":"phoenix-nightmare","Source":"steam","AppId":"2188230","Logo":"https://gamecharts.org/data/steam/img/2188230/header.jpg"},
{"Name":"Phoenix Point","NameSEO":"phoenix-point","Source":"steam","AppId":"839770","Logo":"https://gamecharts.org/data/steam/img/839770/header.jpg"},
{"Name":"Phoenix Point Workshop Tool","NameSEO":"phoenix-point-workshop-tool","Source":"steam","AppId":"1996080","Logo":"https://gamecharts.org/data/steam/img/1996080/header.jpg"},
{"Name":"Phoenix Pro Theater Media Player","NameSEO":"phoenix-pro-theater-media-player","Source":"steam","AppId":"1727320","Logo":"https://gamecharts.org/data/steam/img/1727320/header.jpg"},
{"Name":"Phoenix Springs","NameSEO":"phoenix-springs","Source":"steam","AppId":"1973310","Logo":"https://gamecharts.org/data/steam/img/1973310/header.jpg"},
{"Name":"Phoenix Springs: Prologue","NameSEO":"phoenix-springs-prologue","Source":"steam","AppId":"2390140","Logo":"https://gamecharts.org/data/steam/img/2390140/header.jpg"},
{"Name":"Phoenix Squadron","NameSEO":"phoenix-squadron","Source":"steam","AppId":"1490010","Logo":"https://gamecharts.org/data/steam/img/1490010/header.jpg"},
{"Name":"Phoenix Strike","NameSEO":"phoenix-strike","Source":"steam","AppId":"1237460","Logo":"https://gamecharts.org/data/steam/img/1237460/header.jpg"},
{"Name":"Phoenix Tales","NameSEO":"phoenix-tales","Source":"steam","AppId":"1187490","Logo":"https://gamecharts.org/data/steam/img/1187490/header.jpg"},
{"Name":"Phoenix Wright: Ace Attorney Trilogy","NameSEO":"phoenix-wright-ace-attorney-trilogy","Source":"steam","AppId":"787480","Logo":"https://gamecharts.org/data/steam/img/787480/header.jpg"},
{"Name":"Phoenotopia Awakening","NameSEO":"phoenotopia-awakening","Source":"steam","AppId":"1436590","Logo":"https://gamecharts.org/data/steam/img/1436590/header.jpg"},
{"Name":"Phogbound","NameSEO":"phogbound","Source":"steam","AppId":"1304520","Logo":"https://gamecharts.org/data/steam/img/1304520/header.jpg"},
{"Name":"PHOGS!","NameSEO":"phogs","Source":"steam","AppId":"850320","Logo":"https://gamecharts.org/data/steam/img/850320/header.jpg"},
{"Name":"Phone Seller Simulator","NameSEO":"phone-seller-simulator","Source":"steam","AppId":"1986970","Logo":"https://gamecharts.org/data/steam/img/1986970/header.jpg"},
{"Name":"Phone Simulator","NameSEO":"phone-simulator","Source":"steam","AppId":"1765340","Logo":"https://gamecharts.org/data/steam/img/1765340/header.jpg"},
{"Name":"Phones not Allowed","NameSEO":"phones-not-allowed","Source":"steam","AppId":"2192020","Logo":"https://gamecharts.org/data/steam/img/2192020/header.jpg"},
{"Name":"Phonetic","NameSEO":"phonetic","Source":"steam","AppId":"1881270","Logo":"https://gamecharts.org/data/steam/img/1881270/header.jpg"},
{"Name":"Phoning Home","NameSEO":"phoning-home","Source":"steam","AppId":"431650","Logo":"https://gamecharts.org/data/steam/img/431650/header.jpg"},
{"Name":"Phonk Cats","NameSEO":"phonk-cats","Source":"steam","AppId":"2430790","Logo":"https://gamecharts.org/data/steam/img/2430790/header.jpg"},
{"Name":"Phonopolis","NameSEO":"phonopolis","Source":"steam","AppId":"1206070","Logo":"https://gamecharts.org/data/steam/img/1206070/header.jpg"},
{"Name":"Phos","NameSEO":"phos","Source":"steam","AppId":"1260150","Logo":"https://gamecharts.org/data/steam/img/1260150/header.jpg"},
{"Name":"Photo & Graphic Designer 12 Steam Edition","NameSEO":"photo--graphic-designer-12-steam-edition","Source":"steam","AppId":"596140","Logo":"https://gamecharts.org/data/steam/img/596140/header.jpg"},
{"Name":"Photo & Graphic Designer 15 Steam Edition","NameSEO":"photo--graphic-designer-15-steam-edition","Source":"steam","AppId":"770610","Logo":"https://gamecharts.org/data/steam/img/770610/header.jpg"},
{"Name":"Photo & Graphic Designer 16 Steam Edition","NameSEO":"photo--graphic-designer-16-steam-edition","Source":"steam","AppId":"961990","Logo":"https://gamecharts.org/data/steam/img/961990/header.jpg"},
{"Name":"Photo Finish","NameSEO":"photo-finish","Source":"steam","AppId":"943950","Logo":"https://gamecharts.org/data/steam/img/943950/header.jpg"},
{"Name":"Photo Puzzles HD","NameSEO":"photo-puzzles-hd","Source":"steam","AppId":"1716160","Logo":"https://gamecharts.org/data/steam/img/1716160/header.jpg"},
{"Name":"Photo Quiz - Animals","NameSEO":"photo-quiz---animals","Source":"steam","AppId":"1203580","Logo":"https://gamecharts.org/data/steam/img/1203580/header.jpg"},
{"Name":"Photo Studio","NameSEO":"photo-studio","Source":"steam","AppId":"1384390","Logo":"https://gamecharts.org/data/steam/img/1384390/header.jpg"},
{"Name":"Photo-Life - Rina's Journey","NameSEO":"photo-life---rinas-journey","Source":"steam","AppId":"1573420","Logo":"https://gamecharts.org/data/steam/img/1573420/header.jpg"},
{"Name":"Photo-Toy - Ocean","NameSEO":"photo-toy---ocean","Source":"steam","AppId":"2145860","Logo":"https://gamecharts.org/data/steam/img/2145860/header.jpg"},
{"Name":"Photoelektric","NameSEO":"photoelektric","Source":"steam","AppId":"2063660","Logo":"https://gamecharts.org/data/steam/img/2063660/header.jpg"},
{"Name":"Photoelektric Playtest","NameSEO":"photoelektric-playtest","Source":"steam","AppId":"2063670","Logo":"https://gamecharts.org/data/steam/img/2063670/header.jpg"},
{"Name":"Photogenic Minds : Identity","NameSEO":"photogenic-minds--identity","Source":"steam","AppId":"2074910","Logo":"https://gamecharts.org/data/steam/img/2074910/header.jpg"},
{"Name":"Photographer","NameSEO":"photographer","Source":"steam","AppId":"1562800","Logo":"https://gamecharts.org/data/steam/img/1562800/header.jpg"},
{"Name":"Photographer Simulation","NameSEO":"photographer-simulation","Source":"steam","AppId":"2238300","Logo":"https://gamecharts.org/data/steam/img/2238300/header.jpg"},
{"Name":"Photographs","NameSEO":"photographs","Source":"steam","AppId":"1008920","Logo":"https://gamecharts.org/data/steam/img/1008920/header.jpg"},
{"Name":"Photography Simulator","NameSEO":"photography-simulator","Source":"steam","AppId":"1732910","Logo":"https://gamecharts.org/data/steam/img/1732910/header.jpg"},
{"Name":"PHOTON CUBE","NameSEO":"photon-cube","Source":"steam","AppId":"867510","Logo":"https://gamecharts.org/data/steam/img/867510/header.jpg"},
{"Name":"Photon Engineer","NameSEO":"photon-engineer","Source":"steam","AppId":"2305110","Logo":"https://gamecharts.org/data/steam/img/2305110/header.jpg"},
{"Name":"Photon Flux","NameSEO":"photon-flux","Source":"steam","AppId":"632580","Logo":"https://gamecharts.org/data/steam/img/632580/header.jpg"},
{"Name":"Photon Rush","NameSEO":"photon-rush","Source":"steam","AppId":"667660","Logo":"https://gamecharts.org/data/steam/img/667660/header.jpg"},
{"Name":"Photonic Distress","NameSEO":"photonic-distress","Source":"steam","AppId":"837850","Logo":"https://gamecharts.org/data/steam/img/837850/header.jpg"},
{"Name":"PhotonVERSE","NameSEO":"photonverse","Source":"steam","AppId":"2262330","Logo":"https://gamecharts.org/data/steam/img/2262330/header.jpg"},
{"Name":"PhotoPad","NameSEO":"photopad","Source":"steam","AppId":"617580","Logo":"https://gamecharts.org/data/steam/img/617580/header.jpg"},
{"Name":"phoToq","NameSEO":"photoq","Source":"steam","AppId":"1798970","Logo":"https://gamecharts.org/data/steam/img/1798970/header.jpg"},
{"Name":"Photos","NameSEO":"photos","Source":"steam","AppId":"1204560","Logo":"https://gamecharts.org/data/steam/img/1204560/header.jpg"},
{"Name":"PhotoStage","NameSEO":"photostage","Source":"steam","AppId":"1318170","Logo":"https://gamecharts.org/data/steam/img/1318170/header.jpg"},
{"Name":"PhotoTangler Collage Maker","NameSEO":"phototangler-collage-maker","Source":"steam","AppId":"586560","Logo":"https://gamecharts.org/data/steam/img/586560/header.jpg"},
{"Name":"PhotoVidShow","NameSEO":"photovidshow","Source":"steam","AppId":"909460","Logo":"https://gamecharts.org/data/steam/img/909460/header.jpg"},
{"Name":"PhotoWorld","NameSEO":"photoworld","Source":"steam","AppId":"1435020","Logo":"https://gamecharts.org/data/steam/img/1435020/header.jpg"},
{"Name":"PhotoWorld: Smooth Сorners","NameSEO":"photoworld-smooth-сorners","Source":"steam","AppId":"1616510","Logo":"https://gamecharts.org/data/steam/img/1616510/header.jpg"},
{"Name":"PhotoZoom Classic 6","NameSEO":"photozoom-classic-6","Source":"steam","AppId":"583860","Logo":"https://gamecharts.org/data/steam/img/583860/header.jpg"},
{"Name":"Phrase Shift","NameSEO":"phrase-shift","Source":"steam","AppId":"535980","Logo":"https://gamecharts.org/data/steam/img/535980/header.jpg"},
{"Name":"Phrixothrix","NameSEO":"phrixothrix","Source":"steam","AppId":"2374580","Logo":"https://gamecharts.org/data/steam/img/2374580/header.jpg"},
{"Name":"Phromg Game","NameSEO":"phromg-game","Source":"steam","AppId":"1990300","Logo":"https://gamecharts.org/data/steam/img/1990300/header.jpg"},
{"Name":"Phucker in the Ashes","NameSEO":"phucker-in-the-ashes","Source":"steam","AppId":"1513530","Logo":"https://gamecharts.org/data/steam/img/1513530/header.jpg"},
{"Name":"Phucker in the Gulag","NameSEO":"phucker-in-the-gulag","Source":"steam","AppId":"1064420","Logo":"https://gamecharts.org/data/steam/img/1064420/header.jpg"},
{"Name":"Phucker in the Rome","NameSEO":"phucker-in-the-rome","Source":"steam","AppId":"1164570","Logo":"https://gamecharts.org/data/steam/img/1164570/header.jpg"},
{"Name":"Phucker in the Woods","NameSEO":"phucker-in-the-woods","Source":"steam","AppId":"1132490","Logo":"https://gamecharts.org/data/steam/img/1132490/header.jpg"},
{"Name":"PHYAKH","NameSEO":"phyakh","Source":"steam","AppId":"2149270","Logo":"https://gamecharts.org/data/steam/img/2149270/header.jpg"},
{"Name":"Phylakterion","NameSEO":"phylakterion","Source":"steam","AppId":"2201070","Logo":"https://gamecharts.org/data/steam/img/2201070/header.jpg"},
{"Name":"PHYSARUM: Slime Mold Simulator","NameSEO":"physarum-slime-mold-simulator","Source":"steam","AppId":"1667120","Logo":"https://gamecharts.org/data/steam/img/1667120/header.jpg"},
{"Name":"PhysDrive","NameSEO":"physdrive","Source":"steam","AppId":"541380","Logo":"https://gamecharts.org/data/steam/img/541380/header.jpg"},
{"Name":"Physica-E","NameSEO":"physica-e","Source":"steam","AppId":"706360","Logo":"https://gamecharts.org/data/steam/img/706360/header.jpg"},
{"Name":"Physical Exorcism: Case 01","NameSEO":"physical-exorcism-case-01","Source":"steam","AppId":"949890","Logo":"https://gamecharts.org/data/steam/img/949890/header.jpg"},
{"Name":"Physical Glitch","NameSEO":"physical-glitch","Source":"steam","AppId":"1206900","Logo":"https://gamecharts.org/data/steam/img/1206900/header.jpg"},
{"Name":"Physical Layer","NameSEO":"physical-layer","Source":"steam","AppId":"2298210","Logo":"https://gamecharts.org/data/steam/img/2298210/header.jpg"},
{"Name":"Physics","NameSEO":"physics","Source":"steam","AppId":"1559670","Logo":"https://gamecharts.org/data/steam/img/1559670/header.jpg"},
{"Name":"Physics Cake","NameSEO":"physics-cake","Source":"steam","AppId":"1488670","Logo":"https://gamecharts.org/data/steam/img/1488670/header.jpg"},
{"Name":"Physics car FOREVER","NameSEO":"physics-car-forever","Source":"steam","AppId":"1538810","Logo":"https://gamecharts.org/data/steam/img/1538810/header.jpg"},
{"Name":"Physics Drop","NameSEO":"physics-drop","Source":"steam","AppId":"1038070","Logo":"https://gamecharts.org/data/steam/img/1038070/header.jpg"},
{"Name":"Physics Drop","NameSEO":"physics-drop","Source":"idcgames","AppId":"149","Logo":"https://download.idcgames.com/games/global_releases/splash/149.png"},
{"Name":"Physics Lab","NameSEO":"physics-lab","Source":"steam","AppId":"2167340","Logo":"https://gamecharts.org/data/steam/img/2167340/header.jpg"},
{"Name":"Physics Playground","NameSEO":"physics-playground","Source":"steam","AppId":"2083730","Logo":"https://gamecharts.org/data/steam/img/2083730/header.jpg"},
{"Name":"Physics Sandbox VR","NameSEO":"physics-sandbox-vr","Source":"steam","AppId":"1403040","Logo":"https://gamecharts.org/data/steam/img/1403040/header.jpg"},
{"Name":"Physics World","NameSEO":"physics-world","Source":"steam","AppId":"1571010","Logo":"https://gamecharts.org/data/steam/img/1571010/header.jpg"},
{"Name":"Physics: Optics Table","NameSEO":"physics-optics-table","Source":"steam","AppId":"1058410","Logo":"https://gamecharts.org/data/steam/img/1058410/header.jpg"},
{"Name":"PhyTetris-Physics Tetris","NameSEO":"phytetris-physics-tetris","Source":"steam","AppId":"1778780","Logo":"https://gamecharts.org/data/steam/img/1778780/header.jpg"},
{"Name":"PhyxBox","NameSEO":"phyxbox","Source":"steam","AppId":"1208380","Logo":"https://gamecharts.org/data/steam/img/1208380/header.jpg"}
]
