[
{"Name":"九州仙玉 Kyushu jade","NameSEO":"九州仙玉-kyushu-jade","Source":"steam","AppId":"1203900","Logo":"https://gamecharts.org/data/steam/img/1203900/header.jpg"},
{"Name":"九州战歌","NameSEO":"九州战歌","Source":"steam","AppId":"1739610","Logo":"https://gamecharts.org/data/steam/img/1739610/header.jpg"},
{"Name":"九州谕","NameSEO":"九州谕","Source":"steam","AppId":"2236580","Logo":"https://gamecharts.org/data/steam/img/2236580/header.jpg"},
{"Name":"九州风流","NameSEO":"九州风流","Source":"steam","AppId":"1828540","Logo":"https://gamecharts.org/data/steam/img/1828540/header.jpg"},
{"Name":"九州风流 Playtest","NameSEO":"九州风流-playtest","Source":"steam","AppId":"1832800","Logo":"https://gamecharts.org/data/steam/img/1832800/header.jpg"},
{"Name":"九州：商旅（Nine Provinces: Caravan）","NameSEO":"九州：商旅（nine-provinces-caravan）","Source":"steam","AppId":"908100","Logo":"https://gamecharts.org/data/steam/img/908100/header.jpg"}
]
