[
{"Name":"完美决策 Perfect Decision","NameSEO":"完美决策-perfect-decision","Source":"steam","AppId":"1478440","Logo":"https://gamecharts.org/data/steam/img/1478440/header.jpg"},
{"Name":"完美电路 Electric Circuit","NameSEO":"完美电路-electric-circuit","Source":"steam","AppId":"1357020","Logo":"https://gamecharts.org/data/steam/img/1357020/header.jpg"},
{"Name":"完美的一天 / A Perfect Day","NameSEO":"完美的一天--a-perfect-day","Source":"steam","AppId":"843810","Logo":"https://gamecharts.org/data/steam/img/843810/header.jpg"}
]
