[
{"Name":"忍者お手玉R","NameSEO":"忍者お手玉r","Source":"steam","AppId":"2323630","Logo":"https://gamecharts.org/data/steam/img/2323630/header.jpg"},
{"Name":"忍者快递","NameSEO":"忍者快递","Source":"steam","AppId":"1756810","Logo":"https://gamecharts.org/data/steam/img/1756810/header.jpg"},
{"Name":"忍者明 / Ninja Ming","NameSEO":"忍者明--ninja-ming","Source":"steam","AppId":"1504140","Logo":"https://gamecharts.org/data/steam/img/1504140/header.jpg"},
{"Name":"忍者村大战RC2","NameSEO":"忍者村大战rc2","Source":"steam","AppId":"754350","Logo":"https://gamecharts.org/data/steam/img/754350/header.jpg"}
]
