[
{"Name":"愛する妻、渚の浮気告白 奥ゆかしい妻のカラダが、あいつの激ピストンでとろけていた真実","NameSEO":"愛する妻、渚の浮気告白-奥ゆかしい妻のカラダが、あいつの激ピストンでとろけていた真実","Source":"steam","AppId":"2473000","Logo":"https://gamecharts.org/data/steam/img/2473000/header.jpg"},
{"Name":"愛する妻、玲奈の浮気告白 『お、俺より気持ち良かったのか…？』→『…うん。凄かった』","NameSEO":"愛する妻、玲奈の浮気告白-『お、俺より気持ち良かったのか…？』→『…うん。凄かった』","Source":"steam","AppId":"2285330","Logo":"https://gamecharts.org/data/steam/img/2285330/header.jpg"},
{"Name":"愛する妻、美咲の不倫証拠 『旦那とどっちが気持ちいい？』→『貴方の方が…あっ、ダメッ、またイッちゃうッ…！』","NameSEO":"愛する妻、美咲の不倫証拠-『旦那とどっちが気持ちいい？』→『貴方の方が…あっ、ダメッ、またイッちゃうッ…！』","Source":"steam","AppId":"2285320","Logo":"https://gamecharts.org/data/steam/img/2285320/header.jpg"},
{"Name":"愛する妻が目の前で他人棒に貫かれ、よがり喘いでいく ～ゴメンなさいあなた。でも、私気持ちいいの…～","NameSEO":"愛する妻が目の前で他人棒に貫かれ、よがり喘いでいく-～ゴメンなさいあなた。でも、私気持ちいいの…～","Source":"steam","AppId":"2285340","Logo":"https://gamecharts.org/data/steam/img/2285340/header.jpg"},
{"Name":"愛する妻の穴は他人の穴だった…… ～美尻を差しだし、兄貴の肉棒をおねだりする淫ら妻～","NameSEO":"愛する妻の穴は他人の穴だった……-～美尻を差しだし、兄貴の肉棒をおねだりする淫ら妻～","Source":"steam","AppId":"2470020","Logo":"https://gamecharts.org/data/steam/img/2470020/header.jpg"}
]
