[{"Date":"20/02/20","Average":"388,71"},{"Date":"21/02/20","Average":"240,42"},{"Date":"22/02/20","Average":"277,92"},{"Date":"23/02/20","Average":"260,13"},{"Date":"24/02/20","Average":"191,96"},{"Date":"25/02/20","Average":"182,46"},{"Date":"26/02/20","Average":"176,96"},{"Date":"27/02/20","Average":"181,21"},{"Date":"28/02/20","Average":"201,08"},{"Date":"29/02/20","Average":"246,21"},{"Date":"01/03/20","Average":"241,88"},{"Date":"02/03/20","Average":"198,5"},{"Date":"03/03/20","Average":"187,04"},{"Date":"04/03/20","Average":"184,79"},{"Date":"05/03/20","Average":"176,21"},{"Date":"06/03/20","Average":"196,25"},{"Date":"07/03/20","Average":"246,92"},{"Date":"08/03/20","Average":"253,08"},{"Date":"09/03/20","Average":"178,29"},{"Date":"10/03/20","Average":"180,17"},{"Date":"11/03/20","Average":"186,13"},{"Date":"12/03/20","Average":"193,71"},{"Date":"13/03/20","Average":"237,63"},{"Date":"14/03/20","Average":"282,25"},{"Date":"15/03/20","Average":"302,25"},{"Date":"16/03/20","Average":"319,96"},{"Date":"17/03/20","Average":"339,96"},{"Date":"18/03/20","Average":"349,71"},{"Date":"19/03/20","Average":"339,21"},{"Date":"20/03/20","Average":"342,08"},{"Date":"21/03/20","Average":"365,54"},{"Date":"22/03/20","Average":"405,13"},{"Date":"23/03/20","Average":"389,63"},{"Date":"24/03/20","Average":"366,5"},{"Date":"25/03/20","Average":"377,25"},{"Date":"26/03/20","Average":"384"},{"Date":"27/03/20","Average":"386,54"},{"Date":"28/03/20","Average":"391,75"},{"Date":"29/03/20","Average":"439,13"},{"Date":"30/03/20","Average":"387,83"},{"Date":"31/03/20","Average":"374,83"},{"Date":"01/04/20","Average":"347,04"},{"Date":"02/04/20","Average":"358,17"},{"Date":"03/04/20","Average":"362,33"},{"Date":"04/04/20","Average":"374,21"},{"Date":"05/04/20","Average":"362,13"},{"Date":"06/04/20","Average":"346,83"},{"Date":"07/04/20","Average":"352,33"},{"Date":"08/04/20","Average":"451,14"},{"Date":"09/04/20","Average":"373,04"},{"Date":"10/04/20","Average":"361,38"},{"Date":"11/04/20","Average":"364,67"},{"Date":"12/04/20","Average":"381,48"},{"Date":"13/04/20","Average":"399,77"},{"Date":"14/04/20","Average":"378,71"},{"Date":"15/04/20","Average":"343,67"},{"Date":"16/04/20","Average":"349,96"},{"Date":"17/04/20","Average":"348,08"},{"Date":"18/04/20","Average":"343,17"},{"Date":"19/04/20","Average":"340,71"},{"Date":"20/04/20","Average":"331,71"},{"Date":"21/04/20","Average":"330,08"},{"Date":"22/04/20","Average":"326,25"},{"Date":"23/04/20","Average":"325,63"},{"Date":"24/04/20","Average":"435,33"},{"Date":"25/04/20","Average":"514,33"},{"Date":"26/04/20","Average":"334,92"},{"Date":"27/04/20","Average":"316,04"},{"Date":"28/04/20","Average":"314,96"},{"Date":"29/04/20","Average":"314,46"},{"Date":"30/04/20","Average":"309,79"},{"Date":"01/05/20","Average":"328,04"},{"Date":"02/05/20","Average":"331,25"},{"Date":"03/05/20","Average":"520,5"},{"Date":"04/05/20","Average":"302,04"},{"Date":"05/05/20","Average":"282,96"},{"Date":"06/05/20","Average":"279,13"},{"Date":"07/05/20","Average":"271"},{"Date":"08/05/20","Average":"250,71"},{"Date":"09/05/20","Average":"246,25"},{"Date":"10/05/20","Average":"244,17"},{"Date":"11/05/20","Average":"188,54"},{"Date":"12/05/20","Average":"216,5"},{"Date":"13/05/20","Average":"200,04"},{"Date":"14/05/20","Average":"200,79"},{"Date":"15/05/20","Average":"187,13"},{"Date":"16/05/20","Average":"182,96"},{"Date":"17/05/20","Average":"191,63"},{"Date":"18/05/20","Average":"188,75"},{"Date":"19/05/20","Average":"186,25"},{"Date":"20/05/20","Average":"187,71"},{"Date":"21/05/20","Average":"184,54"},{"Date":"22/05/20","Average":"177,75"},{"Date":"23/05/20","Average":"187,29"},{"Date":"24/05/20","Average":"192,13"},{"Date":"25/05/20","Average":"181,29"},{"Date":"26/05/20","Average":"187,33"},{"Date":"27/05/20","Average":"177,25"},{"Date":"28/05/20","Average":"188,08"},{"Date":"29/05/20","Average":"177,5"},{"Date":"30/05/20","Average":"129"},{"Date":"31/05/20","Average":"206,67"},{"Date":"01/06/20","Average":"173,63"},{"Date":"02/06/20","Average":"137,89"},{"Date":"03/06/20","Average":"176,88"},{"Date":"04/06/20","Average":"169,83"},{"Date":"05/06/20","Average":"168,42"},{"Date":"06/06/20","Average":"169,88"},{"Date":"07/06/20","Average":"178"},{"Date":"08/06/20","Average":"181,13"},{"Date":"09/06/20","Average":"141,42"},{"Date":"10/06/20","Average":"167,04"},{"Date":"11/06/20","Average":"157,58"},{"Date":"12/06/20","Average":"151,5"},{"Date":"13/06/20","Average":"143,67"},{"Date":"14/06/20","Average":"159,08"},{"Date":"15/06/20","Average":"155,88"},{"Date":"16/06/20","Average":"152,21"},{"Date":"17/06/20","Average":"147,17"},{"Date":"18/06/20","Average":"141,17"},{"Date":"19/06/20","Average":"134,88"},{"Date":"20/06/20","Average":"148,96"},{"Date":"21/06/20","Average":"157,92"},{"Date":"22/06/20","Average":"151,38"},{"Date":"23/06/20","Average":"152,63"},{"Date":"24/06/20","Average":"133"},{"Date":"25/06/20","Average":"126,71"},{"Date":"26/06/20","Average":"126,71"},{"Date":"27/06/20","Average":"132,5"},{"Date":"28/06/20","Average":"128,88"},{"Date":"29/06/20","Average":"140,92"},{"Date":"30/06/20","Average":"131,04"},{"Date":"01/07/20","Average":"123,92"},{"Date":"02/07/20","Average":"122,25"},{"Date":"03/07/20","Average":"118,5"},{"Date":"04/07/20","Average":"116,38"},{"Date":"05/07/20","Average":"121,04"},{"Date":"06/07/20","Average":"126,88"},{"Date":"07/07/20","Average":"127,13"},{"Date":"08/07/20","Average":"125,92"},{"Date":"09/07/20","Average":"115,58"},{"Date":"10/07/20","Average":"82,7"},{"Date":"15/07/20","Average":"132"},{"Date":"16/07/20","Average":"104,13"},{"Date":"17/07/20","Average":"106,58"},{"Date":"18/07/20","Average":"108,83"},{"Date":"19/07/20","Average":"86,17"},{"Date":"20/07/20","Average":"104,25"},{"Date":"21/07/20","Average":"64,67"},{"Date":"22/07/20","Average":"147"},{"Date":"23/07/20","Average":"97,96"},{"Date":"24/07/20","Average":"97,5"},{"Date":"25/07/20","Average":"101,42"},{"Date":"26/07/20","Average":"99,5"},{"Date":"27/07/20","Average":"98,42"},{"Date":"28/07/20","Average":"96,33"},{"Date":"29/07/20","Average":"92,46"},{"Date":"30/07/20","Average":"96,92"},{"Date":"31/07/20","Average":"97,08"},{"Date":"01/08/20","Average":"96,38"},{"Date":"02/08/20","Average":"96,17"},{"Date":"03/08/20","Average":"100,63"},{"Date":"04/08/20","Average":"86"},{"Date":"05/08/20","Average":"91,71"},{"Date":"06/08/20","Average":"97,79"},{"Date":"07/08/20","Average":"88,79"},{"Date":"08/08/20","Average":"85,96"},{"Date":"09/08/20","Average":"91,29"},{"Date":"10/08/20","Average":"95,42"},{"Date":"11/08/20","Average":"87,75"},{"Date":"12/08/20","Average":"82,46"},{"Date":"13/08/20","Average":"80,79"},{"Date":"14/08/20","Average":"82,13"},{"Date":"15/08/20","Average":"83,96"},{"Date":"16/08/20","Average":"87,83"},{"Date":"17/08/20","Average":"90,33"},{"Date":"18/08/20","Average":"92,25"},{"Date":"19/08/20","Average":"84,63"},{"Date":"20/08/20","Average":"76,54"},{"Date":"21/08/20","Average":"87"},{"Date":"22/08/20","Average":"90,29"},{"Date":"23/08/20","Average":"92,08"},{"Date":"24/08/20","Average":"97,29"},{"Date":"25/08/20","Average":"95,75"},{"Date":"26/08/20","Average":"90,54"},{"Date":"27/08/20","Average":"65,88"},{"Date":"28/08/20","Average":"80"},{"Date":"29/08/20","Average":"92,96"},{"Date":"30/08/20","Average":"104,17"},{"Date":"31/08/20","Average":"101,33"},{"Date":"01/09/20","Average":"93,96"},{"Date":"02/09/20","Average":"86,63"},{"Date":"03/09/20","Average":"82,92"},{"Date":"04/09/20","Average":"86,04"},{"Date":"05/09/20","Average":"95,08"},{"Date":"06/09/20","Average":"99,63"},{"Date":"07/09/20","Average":"86,63"},{"Date":"08/09/20","Average":"78,92"},{"Date":"09/09/20","Average":"64"},{"Date":"10/09/20","Average":"85,71"},{"Date":"11/09/20","Average":"79,42"},{"Date":"12/09/20","Average":"82,17"},{"Date":"13/09/20","Average":"87,21"},{"Date":"14/09/20","Average":"81,04"},{"Date":"15/09/20","Average":"67,5"},{"Date":"16/09/20","Average":"63,13"},{"Date":"17/09/20","Average":"67"},{"Date":"18/09/20","Average":"72,21"},{"Date":"19/09/20","Average":"83,5"},{"Date":"20/09/20","Average":"84,83"},{"Date":"21/09/20","Average":"74,54"},{"Date":"22/09/20","Average":"66,54"},{"Date":"23/09/20","Average":"72,63"},{"Date":"24/09/20","Average":"67,17"},{"Date":"25/09/20","Average":"77,17"},{"Date":"26/09/20","Average":"90,17"},{"Date":"27/09/20","Average":"86,04"},{"Date":"28/09/20","Average":"73,63"},{"Date":"29/09/20","Average":"74,33"},{"Date":"30/09/20","Average":"66,42"},{"Date":"01/10/20","Average":"69,79"},{"Date":"02/10/20","Average":"70,33"},{"Date":"03/10/20","Average":"78,13"},{"Date":"04/10/20","Average":"83,04"},{"Date":"05/10/20","Average":"75,58"},{"Date":"06/10/20","Average":"64,46"},{"Date":"07/10/20","Average":"67,83"},{"Date":"08/10/20","Average":"66,25"},{"Date":"09/10/20","Average":"75,08"},{"Date":"10/10/20","Average":"86,13"},{"Date":"11/10/20","Average":"90,38"},{"Date":"12/10/20","Average":"66,25"},{"Date":"13/10/20","Average":"27"},{"Date":"15/10/20","Average":"113,33"},{"Date":"16/10/20","Average":"53,46"},{"Date":"17/10/20","Average":"51,75"},{"Date":"18/10/20","Average":"54,13"},{"Date":"19/10/20","Average":"45,42"},{"Date":"20/10/20","Average":"40,88"},{"Date":"21/10/20","Average":"40,04"},{"Date":"22/10/20","Average":"40,63"},{"Date":"23/10/20","Average":"39,5"},{"Date":"24/10/20","Average":"43,25"},{"Date":"25/10/20","Average":"45,83"},{"Date":"26/10/20","Average":"39,33"},{"Date":"27/10/20","Average":"38,58"},{"Date":"28/10/20","Average":"34,08"},{"Date":"29/10/20","Average":"37,79"},{"Date":"30/10/20","Average":"36,17"},{"Date":"31/10/20","Average":"37,92"},{"Date":"01/11/20","Average":"40,17"},{"Date":"02/11/20","Average":"29,17"},{"Date":"03/11/20","Average":"31,13"},{"Date":"04/11/20","Average":"34,71"},{"Date":"05/11/20","Average":"30,63"},{"Date":"06/11/20","Average":"29,54"},{"Date":"07/11/20","Average":"34,13"},{"Date":"08/11/20","Average":"33,96"},{"Date":"09/11/20","Average":"32,04"},{"Date":"10/11/20","Average":"28"},{"Date":"11/11/20","Average":"31,63"},{"Date":"12/11/20","Average":"29,38"},{"Date":"13/11/20","Average":"34,88"},{"Date":"14/11/20","Average":"36,71"},{"Date":"15/11/20","Average":"35,83"},{"Date":"16/11/20","Average":"31,33"},{"Date":"17/11/20","Average":"29,25"},{"Date":"18/11/20","Average":"26,08"},{"Date":"19/11/20","Average":"25,75"},{"Date":"20/11/20","Average":"25,83"},{"Date":"21/11/20","Average":"30"},{"Date":"22/11/20","Average":"29,83"},{"Date":"23/11/20","Average":"23,63"},{"Date":"24/11/20","Average":"22,92"},{"Date":"25/11/20","Average":"22,71"},{"Date":"26/11/20","Average":"24,46"},{"Date":"27/11/20","Average":"25,79"},{"Date":"28/11/20","Average":"28"},{"Date":"29/11/20","Average":"30,17"},{"Date":"30/11/20","Average":"25,88"},{"Date":"01/12/20","Average":"22,21"},{"Date":"02/12/20","Average":"24,13"},{"Date":"03/12/20","Average":"26,5"},{"Date":"04/12/20","Average":"24,29"},{"Date":"05/12/20","Average":"24,58"},{"Date":"06/12/20","Average":"28,17"},{"Date":"07/12/20","Average":"25,92"},{"Date":"08/12/20","Average":"22,13"},{"Date":"09/12/20","Average":"23,96"},{"Date":"10/12/20","Average":"23,04"},{"Date":"11/12/20","Average":"19,04"},{"Date":"12/12/20","Average":"24,21"},{"Date":"13/12/20","Average":"14,83"},{"Date":"14/12/20","Average":"23,71"},{"Date":"15/12/20","Average":"21,88"},{"Date":"16/12/20","Average":"20,08"},{"Date":"17/12/20","Average":"23,71"},{"Date":"18/12/20","Average":"23,96"},{"Date":"19/12/20","Average":"25,46"},{"Date":"20/12/20","Average":"26,92"},{"Date":"21/12/20","Average":"24,83"},{"Date":"22/12/20","Average":"22,13"},{"Date":"23/12/20","Average":"20,96"},{"Date":"24/12/20","Average":"21,17"},{"Date":"25/12/20","Average":"25,88"},{"Date":"26/12/20","Average":"27,79"},{"Date":"27/12/20","Average":"26"},{"Date":"28/12/20","Average":"24,42"},{"Date":"29/12/20","Average":"23,54"},{"Date":"30/12/20","Average":"25,5"},{"Date":"31/12/20","Average":"24,5"},{"Date":"01/01/21","Average":"27,5"},{"Date":"02/01/21","Average":"26,33"},{"Date":"03/01/21","Average":"29,04"},{"Date":"04/01/21","Average":"28,17"},{"Date":"05/01/21","Average":"24,54"},{"Date":"06/01/21","Average":"24,08"},{"Date":"07/01/21","Average":"24,58"},{"Date":"08/01/21","Average":"25,96"},{"Date":"09/01/21","Average":"25,38"},{"Date":"10/01/21","Average":"26,88"},{"Date":"11/01/21","Average":"19,38"},{"Date":"12/01/21","Average":"16,04"},{"Date":"13/01/21","Average":"20,08"},{"Date":"14/01/21","Average":"20,08"},{"Date":"15/01/21","Average":"22,88"},{"Date":"16/01/21","Average":"24,79"},{"Date":"17/01/21","Average":"25,21"},{"Date":"18/01/21","Average":"6,92"},{"Date":"19/01/21","Average":"1,88"},{"Date":"20/01/21","Average":"1,08"},{"Date":"21/01/21","Average":"1,08"},{"Date":"22/01/21","Average":"1,21"},{"Date":"23/01/21","Average":"1,05"},{"Date":"24/01/21","Average":"1,04"},{"Date":"25/01/21","Average":"1"},{"Date":"26/01/21","Average":"1,04"},{"Date":"27/01/21","Average":"1,04"},{"Date":"28/01/21","Average":"1"},{"Date":"29/01/21","Average":"1"},{"Date":"30/01/21","Average":"1"},{"Date":"31/01/21","Average":"1"},{"Date":"01/02/21","Average":"1"},{"Date":"02/02/21","Average":"1"},{"Date":"03/02/21","Average":"1"},{"Date":"04/02/21","Average":"1"},{"Date":"05/02/21","Average":"1"},{"Date":"06/02/21","Average":"1"},{"Date":"07/02/21","Average":"1"},{"Date":"08/02/21","Average":"1"},{"Date":"21/02/21","Average":"1"}]