[{"Date":"20/02/20","Average":"388,71"},{"Date":"21/02/20","Average":"240,42"},{"Date":"22/02/20","Average":"277,92"},{"Date":"23/02/20","Average":"260,13"},{"Date":"24/02/20","Average":"191,96"},{"Date":"25/02/20","Average":"182,46"},{"Date":"26/02/20","Average":"176,96"},{"Date":"27/02/20","Average":"181,21"},{"Date":"28/02/20","Average":"201,08"},{"Date":"29/02/20","Average":"246,21"},{"Date":"01/03/20","Average":"241,88"},{"Date":"02/03/20","Average":"198,5"},{"Date":"03/03/20","Average":"187,04"},{"Date":"04/03/20","Average":"184,79"},{"Date":"05/03/20","Average":"176,21"},{"Date":"06/03/20","Average":"196,25"},{"Date":"07/03/20","Average":"246,92"},{"Date":"08/03/20","Average":"253,08"},{"Date":"09/03/20","Average":"178,29"},{"Date":"10/03/20","Average":"180,17"},{"Date":"11/03/20","Average":"186,13"},{"Date":"12/03/20","Average":"193,71"},{"Date":"13/03/20","Average":"237,63"},{"Date":"14/03/20","Average":"282,25"},{"Date":"15/03/20","Average":"302,25"},{"Date":"16/03/20","Average":"319,96"},{"Date":"17/03/20","Average":"339,96"},{"Date":"18/03/20","Average":"349,71"},{"Date":"19/03/20","Average":"339,21"},{"Date":"20/03/20","Average":"342,08"},{"Date":"21/03/20","Average":"365,54"},{"Date":"22/03/20","Average":"405,13"},{"Date":"23/03/20","Average":"389,63"},{"Date":"24/03/20","Average":"366,5"},{"Date":"25/03/20","Average":"377,25"},{"Date":"26/03/20","Average":"384"},{"Date":"27/03/20","Average":"386,54"},{"Date":"28/03/20","Average":"391,75"},{"Date":"29/03/20","Average":"439,13"},{"Date":"30/03/20","Average":"387,83"},{"Date":"31/03/20","Average":"374,83"},{"Date":"01/04/20","Average":"347,04"},{"Date":"02/04/20","Average":"358,17"},{"Date":"03/04/20","Average":"362,33"},{"Date":"04/04/20","Average":"374,21"},{"Date":"05/04/20","Average":"362,13"},{"Date":"06/04/20","Average":"346,83"},{"Date":"07/04/20","Average":"352,33"},{"Date":"08/04/20","Average":"451,14"},{"Date":"09/04/20","Average":"373,04"},{"Date":"10/04/20","Average":"361,38"},{"Date":"11/04/20","Average":"364,67"},{"Date":"12/04/20","Average":"381,48"},{"Date":"13/04/20","Average":"399,77"},{"Date":"14/04/20","Average":"378,71"},{"Date":"15/04/20","Average":"343,67"},{"Date":"16/04/20","Average":"349,96"},{"Date":"17/04/20","Average":"348,08"},{"Date":"18/04/20","Average":"343,17"},{"Date":"19/04/20","Average":"340,71"},{"Date":"20/04/20","Average":"331,71"},{"Date":"21/04/20","Average":"330,08"},{"Date":"22/04/20","Average":"326,25"},{"Date":"23/04/20","Average":"325,63"},{"Date":"24/04/20","Average":"435,33"},{"Date":"25/04/20","Average":"514,33"},{"Date":"26/04/20","Average":"225,94"}]